llama_index/tools/openai/__init__.py
llama_index/tools/openai/image_generation/__init__.py
llama_index/tools/openai/image_generation/base.py
llama_index_tools_openai_image_generation-0.5.1.dist-info/METADATA
llama_index_tools_openai_image_generation-0.5.1.dist-info/WHEEL
llama_index_tools_openai_image_generation-0.5.1.dist-info/licenses/LICENSE
llama_index_tools_openai_image_generation-0.5.1.dist-info/RECORD
