Metadata-Version: 2.4
Name: llama-index-tools-openai-image-generation
Version: 0.5.1
Summary: llama-index tools openai_image_generation integration
Author-email: Your Name <you@example.com>
Maintainer: manelferreira_
License-Expression: MIT
License-File: LICENSE
Keywords: cv,gpt-3,image,openai,vision
Requires-Python: <4.0,>=3.9
Requires-Dist: llama-index-core<0.15,>=0.13.0
